[
  {
    "user_id": "U1001",
    "txn_id": 1,
    "event_time": "2026-03-01T09:00:00",
    "event_type": "deposit",
    "amount": 500,
    "currency": "usd",
    "channel": "mobile",
    "declared_income": 5000,
    "account_deposit": 3000,
    "residence_country": "us",
    "transaction_country": "us",
    "amount_in_1d": 500,
    "amount_out_1d": 0,
    "login_count_1h": 3,
    "failed_login_1h": 0,
    "new_ip_1d": 0,
    "geo_change_1d": 0
  },
  {
    "user_id": "U1001",
    "txn_id": 2,
    "event_time": "2026-03-01T12:00:00",
    "event_type": "buy",
    "amount": 200,
    "currency": "usd",
    "channel": "mobile",
    "declared_income": 5000,
    "account_deposit": 2800,
    "residence_country": "us",
    "transaction_country": "us",
    "amount_in_1d": 700,
    "amount_out_1d": 0,
    "login_count_1h": 2,
    "failed_login_1h": 0,
    "new_ip_1d": 0,
    "geo_change_1d": 0
  },
  {
    "user_id": "U1001",
    "txn_id": 3,
    "event_time": "2026-03-01T18:00:00",
    "event_type": "withdrawal",
    "amount": 300,
    "currency": "usd",
    "channel": "mobile",
    "declared_income": 5000,
    "account_deposit": 2500,
    "residence_country": "us",
    "transaction_country": "us",
    "amount_in_1d": 700,
    "amount_out_1d": 300,
    "login_count_1h": 2,
    "failed_login_1h": 0,
    "new_ip_1d": 0,
    "geo_change_1d": 0
  },
  {
    "user_id": "U1001",
    "txn_id": 4,
    "event_time": "2026-03-02T09:30:00",
    "event_type": "buy",
    "amount": 150,
    "currency": "usd",
    "channel": "mobile",
    "declared_income": 5000,
    "account_deposit": 2350,
    "residence_country": "us",
    "transaction_country": "us",
    "amount_in_1d": 350,
    "amount_out_1d": 300,
    "login_count_1h": 2,
    "failed_login_1h": 0,
    "new_ip_1d": 0,
    "geo_change_1d": 0
  },
  {
    "user_id": "U2001",
    "txn_id": 5,
    "event_time": "2026-03-01T10:00:00",
    "event_type": "deposit",
    "amount": 800,
    "currency": "usd",
    "channel": "web",
    "declared_income": 6000,
    "account_deposit": 4000,
    "residence_country": "us",
    "transaction_country": "us",
    "amount_in_1d": 800,
    "amount_out_1d": 0,
    "login_count_1h": 4,
    "failed_login_1h": 0,
    "new_ip_1d": 0,
    "geo_change_1d": 0
  },
  {
    "user_id": "U2001",
    "txn_id": 6,
    "event_time": "2026-03-01T15:00:00",
    "event_type": "sell",
    "amount": 300,
    "currency": "usd",
    "channel": "web",
    "declared_income": 6000,
    "account_deposit": 3700,
    "residence_country": "us",
    "transaction_country": "us",
    "amount_in_1d": 800,
    "amount_out_1d": 300,
    "login_count_1h": 3,
    "failed_login_1h": 0,
    "new_ip_1d": 0,
    "geo_change_1d": 0
  },
  {
    "user_id": "U2001",
    "txn_id": 7,
    "event_time": "2026-03-02T11:00:00",
    "event_type": "withdrawal",
    "amount": 500,
    "currency": "usd",
    "channel": "web",
    "declared_income": 6000,
    "account_deposit": 3200,
    "residence_country": "us",
    "transaction_country": "us",
    "amount_in_1d": 800,
    "amount_out_1d": 800,
    "login_count_1h": 3,
    "failed_login_1h": 0,
    "new_ip_1d": 0,
    "geo_change_1d": 0
  },
  {
    "user_id": "U9001",
    "txn_id": 8,
    "event_time": "2026-03-03T01:10:00",
    "event_type": "deposit",
    "amount": 1000,
    "currency": "usd",
    "channel": "mobile",
    "declared_income": 4000,
    "account_deposit": 3500,
    "residence_country": "us",
    "transaction_country": "us",
    "amount_in_1d": 1000,
    "amount_out_1d": 0,
    "login_count_1h": 2,
    "failed_login_1h": 0,
    "new_ip_1d": 0,
    "geo_change_1d": 0
  },
  {
    "user_id": "U9001",
    "txn_id": 9,
    "event_time": "2026-03-03T01:12:00",
    "event_type": "withdrawal",
    "amount": 25000,
    "currency": "usd",
    "channel": "mobile",
    "declared_income": 4000,
    "account_deposit": 1000,
    "residence_country": "us",
    "transaction_country": "sg",
    "amount_in_1d": 1000,
    "amount_out_1d": 25000,
    "login_count_1h": 15,
    "failed_login_1h": 10,
    "new_ip_1d": 1,
    "geo_change_1d": 1
  },
  {
    "user_id": "U9001",
    "txn_id": 10,
    "event_time": "2026-03-03T01:13:00",
    "event_type": "withdrawal",
    "amount": 18000,
    "currency": "usd",
    "channel": "mobile",
    "declared_income": 4000,
    "account_deposit": -17000,
    "residence_country": "us",
    "transaction_country": "sg",
    "amount_in_1d": 1000,
    "amount_out_1d": 43000,
    "login_count_1h": 18,
    "failed_login_1h": 12,
    "new_ip_1d": 1,
    "geo_change_1d": 1
  },
  {
    "user_id": "U9002",
    "txn_id": 11,
    "event_time": "2026-03-04T22:00:00",
    "event_type": "deposit",
    "amount": 600,
    "currency": "usd",
    "channel": "mobile",
    "declared_income": 4500,
    "account_deposit": 2800,
    "residence_country": "us",
    "transaction_country": "us",
    "amount_in_1d": 600,
    "amount_out_1d": 0,
    "login_count_1h": 2,
    "failed_login_1h": 0,
    "new_ip_1d": 0,
    "geo_change_1d": 0
  },
  {
    "user_id": "U9002",
    "txn_id": 12,
    "event_time": "2026-03-04T22:01:00",
    "event_type": "withdrawal",
    "amount": 15000,
    "currency": "usd",
    "channel": "mobile",
    "declared_income": 4500,
    "account_deposit": 500,
    "residence_country": "us",
    "transaction_country": "ru",
    "amount_in_1d": 600,
    "amount_out_1d": 15000,
    "login_count_1h": 12,
    "failed_login_1h": 8,
    "new_ip_1d": 1,
    "geo_change_1d": 1
  },
  {
    "user_id": "U3001",
    "txn_id": 13,
    "event_time": "2026-03-05T09:00:00",
    "event_type": "deposit",
    "amount": 700,
    "currency": "usd",
    "channel": "mobile",
    "declared_income": 5200,
    "account_deposit": 3100,
    "residence_country": "us",
    "transaction_country": "us",
    "amount_in_1d": 700,
    "amount_out_1d": 0,
    "login_count_1h": 3,
    "failed_login_1h": 0,
    "new_ip_1d": 0,
    "geo_change_1d": 0
  },
  {
    "user_id": "U3001",
    "txn_id": 14,
    "event_time": "2026-03-05T13:30:00",
    "event_type": "buy",
    "amount": 250,
    "currency": "usd",
    "channel": "mobile",
    "declared_income": 5200,
    "account_deposit": 2850,
    "residence_country": "us",
    "transaction_country": "us",
    "amount_in_1d": 950,
    "amount_out_1d": 0,
    "login_count_1h": 2,
    "failed_login_1h": 0,
    "new_ip_1d": 0,
    "geo_change_1d": 0
  },
  {
    "user_id": "U3001",
    "txn_id": 15,
    "event_time": "2026-03-05T19:00:00",
    "event_type": "withdrawal",
    "amount": 400,
    "currency": "usd",
    "channel": "mobile",
    "declared_income": 5200,
    "account_deposit": 2450,
    "residence_country": "us",
    "transaction_country": "us",
    "amount_in_1d": 950,
    "amount_out_1d": 400,
    "login_count_1h": 2,
    "failed_login_1h": 0,
    "new_ip_1d": 0,
    "geo_change_1d": 0
  },
  {
    "user_id": "U4001",
    "txn_id": 16,
    "event_time": "2026-03-05T10:00:00",
    "event_type": "deposit",
    "amount": 900,
    "currency": "usd",
    "channel": "web",
    "declared_income": 6500,
    "account_deposit": 4200,
    "residence_country": "us",
    "transaction_country": "us",
    "amount_in_1d": 900,
    "amount_out_1d": 0,
    "login_count_1h": 4,
    "failed_login_1h": 0,
    "new_ip_1d": 0,
    "geo_change_1d": 0
  },
  {
    "user_id": "U4001",
    "txn_id": 17,
    "event_time": "2026-03-05T14:00:00",
    "event_type": "sell",
    "amount": 500,
    "currency": "usd",
    "channel": "web",
    "declared_income": 6500,
    "account_deposit": 3700,
    "residence_country": "us",
    "transaction_country": "us",
    "amount_in_1d": 900,
    "amount_out_1d": 500,
    "login_count_1h": 3,
    "failed_login_1h": 0,
    "new_ip_1d": 0,
    "geo_change_1d": 0
  },
  {
    "user_id": "U4001",
    "txn_id": 18,
    "event_time": "2026-03-05T18:30:00",
    "event_type": "withdrawal",
    "amount": 600,
    "currency": "usd",
    "channel": "web",
    "declared_income": 6500,
    "account_deposit": 3100,
    "residence_country": "us",
    "transaction_country": "us",
    "amount_in_1d": 900,
    "amount_out_1d": 1100,
    "login_count_1h": 3,
    "failed_login_1h": 0,
    "new_ip_1d": 0,
    "geo_change_1d": 0
  },
  {
    "user_id": "U9101",
    "txn_id": 19,
    "event_time": "2026-03-06T00:10:00",
    "event_type": "deposit",
    "amount": 1200,
    "currency": "usd",
    "channel": "mobile",
    "declared_income": 3800,
    "account_deposit": 3400,
    "residence_country": "us",
    "transaction_country": "us",
    "amount_in_1d": 1200,
    "amount_out_1d": 0,
    "login_count_1h": 2,
    "failed_login_1h": 0,
    "new_ip_1d": 0,
    "geo_change_1d": 0
  },
  {
    "user_id": "U9101",
    "txn_id": 20,
    "event_time": "2026-03-06T00:12:00",
    "event_type": "withdrawal",
    "amount": 22000,
    "currency": "usd",
    "channel": "mobile",
    "declared_income": 3800,
    "account_deposit": 1200,
    "residence_country": "us",
    "transaction_country": "cn",
    "amount_in_1d": 1200,
    "amount_out_1d": 22000,
    "login_count_1h": 16,
    "failed_login_1h": 11,
    "new_ip_1d": 1,
    "geo_change_1d": 1
  },
  {
    "user_id": "U9101",
    "txn_id": 21,
    "event_time": "2026-03-06T00:13:00",
    "event_type": "withdrawal",
    "amount": 17000,
    "currency": "usd",
    "channel": "mobile",
    "declared_income": 3800,
    "account_deposit": -15800,
    "residence_country": "us",
    "transaction_country": "cn",
    "amount_in_1d": 1200,
    "amount_out_1d": 39000,
    "login_count_1h": 19,
    "failed_login_1h": 14,
    "new_ip_1d": 1,
    "geo_change_1d": 1
  },
  {
    "user_id": "U9202",
    "txn_id": 22,
    "event_time": "2026-03-07T21:00:00",
    "event_type": "deposit",
    "amount": 650,
    "currency": "usd",
    "channel": "mobile",
    "declared_income": 4800,
    "account_deposit": 2900,
    "residence_country": "us",
    "transaction_country": "us",
    "amount_in_1d": 650,
    "amount_out_1d": 0,
    "login_count_1h": 2,
    "failed_login_1h": 0,
    "new_ip_1d": 0,
    "geo_change_1d": 0
  },
  {
    "user_id": "U9202",
    "txn_id": 23,
    "event_time": "2026-03-07T21:01:00",
    "event_type": "withdrawal",
    "amount": 14000,
    "currency": "usd",
    "channel": "mobile",
    "declared_income": 4800,
    "account_deposit": 600,
    "residence_country": "us",
    "transaction_country": "br",
    "amount_in_1d": 650,
    "amount_out_1d": 14000,
    "login_count_1h": 11,
    "failed_login_1h": 7,
    "new_ip_1d": 1,
    "geo_change_1d": 1
  }
]